README.md
setup.cfg
setup.py
djinn/__init__.py
djinn/app.py
djinn/compat.py
djinn/db.py
djinn/decorators.py
djinn/errors.py
djinn/handler.py
djinn/mail.py
djinn/options.py
djinn/utils.py
djinn/validators.py
djinn.egg-info/PKG-INFO
djinn.egg-info/SOURCES.txt
djinn.egg-info/dependency_links.txt
djinn.egg-info/requires.txt
djinn.egg-info/top_level.txt
djinn/datastore/__init__.py
djinn/datastore/cache.py
djinn/datastore/mysql.py
djinn/datastore/rstore.py
djinn/translations/zh_CN.csv