Metadata-Version: 1.1
Name: djinn
Version: 1.1.14
Summary: Djinn is a micro-framework which wraps Tornado to make it easy to write a web application using Tornado.
Home-page: https://github.com/felinx/djinn
Author: Felinx Lee
Author-email: felinx.lee@gmail.com
License: http://www.apache.org/licenses/LICENSE-2.0
Platform: UNKNOWN
Classifier: Programming Language :: Python :: 2
Classifier: Programming Language :: Python :: 2.7
Classifier: Programming Language :: Python :: 3
Classifier: Programming Language :: Python :: 3.6
